pyedbglib/__init__.py
pyedbglib/pyedbglib_errors.py
pyedbglib/hidtransport/__init__.py
pyedbglib/hidtransport/cyhidapi.py
pyedbglib/hidtransport/hidtransportbase.py
pyedbglib/hidtransport/hidtransportfactory.py
pyedbglib/hidtransport/toolinfo.py
pyedbglib/mplabtransport/__init__.py
pyedbglib/mplabtransport/mplabtransport.py
pyedbglib/primitive/__init__.py
pyedbglib/primitive/gen4controller.py
pyedbglib/primitive/primitivecontroller.py
pyedbglib/primitive/primitives.py
pyedbglib/primitive/spitfirecontroller.py
pyedbglib/protocols/__init__.py
pyedbglib/protocols/ati.py
pyedbglib/protocols/avr32protocol.py
pyedbglib/protocols/avr32protocolerrors.py
pyedbglib/protocols/avr8protocol.py
pyedbglib/protocols/avr8protocolerrors.py
pyedbglib/protocols/avrcmsisdap.py
pyedbglib/protocols/avrispprotocol.py
pyedbglib/protocols/cmsisdap.py
pyedbglib/protocols/configprotocol.py
pyedbglib/protocols/dapcommand.py
pyedbglib/protocols/dapwrapper.py
pyedbglib/protocols/edbgprotocol.py
pyedbglib/protocols/housekeepingprotocol.py
pyedbglib/protocols/jtagice3protocol.py
pyedbglib/protocols/selftestprotocol.py
pyedbglib/protocols/tpiprotocol.py
pyedbglib/serialport/__init__.py
pyedbglib/serialport/serialcdc.py
pyedbglib/serialport/serialportcheck.py
pyedbglib/serialport/serialportmap.py
pyedbglib/util/__init__.py
pyedbglib/util/binary.py
pyedbglib/util/chopper.py
pyedbglib/util/hex_to_uf2.py
pyedbglib/util/print_helpers.py
pyedbglib-2.24.2.18.dist-info/LICENSE.txt
pyedbglib-2.24.2.18.dist-info/METADATA
pyedbglib-2.24.2.18.dist-info/WHEEL
pyedbglib-2.24.2.18.dist-info/top_level.txt
pyedbglib-2.24.2.18.dist-info/RECORD
