Metadata-Version: 2.1
Name: pyedbglib
Version: 2.24.2.18
Summary: Low-level protocol library for communicating with Microchip CMSIS-DAP based debuggers
Author: Microchip Technology
Author-email: support@microchip.com
License: MIT
Keywords: Microchip,AVR,EDBG,protocol
Classifier: Development Status :: 5 - Production/Stable
Classifier: Intended Audience :: Developers
Classifier: Topic :: Software Development :: Embedded Systems
Classifier: Programming Language :: Python :: 2.7
Classifier: Programming Language :: Python :: 3
Classifier: Programming Language :: Python :: 3.8
Classifier: Programming Language :: Python :: 3.9
Classifier: Programming Language :: Python :: 3.10
Classifier: Programming Language :: Python :: 3.11
Classifier: Programming Language :: Python :: 3.12
Classifier: Operating System :: Microsoft :: Windows
Classifier: Operating System :: POSIX :: Linux
Classifier: Operating System :: MacOS
Classifier: License :: OSI Approved :: MIT License
Requires-Python: >=2.7
License-File: LICENSE.txt
Requires-Dist: pyserial >=3.5
Requires-Dist: cython <0.29.8 ; python_version <= "2.7"
Requires-Dist: hidapi ==0.7.99.post21 ; python_version <= "2.7"
Requires-Dist: cython ; python_version >= "3"
Requires-Dist: hidapi ; python_version >= "3"
Provides-Extra: dev
Requires-Dist: pylint >=2.15 ; extra == 'dev'
Provides-Extra: doc
Requires-Dist: mock ; extra == 'doc'
Requires-Dist: sphinx ; extra == 'doc'
Provides-Extra: test
Requires-Dist: mock ; extra == 'test'
Requires-Dist: pytest ; extra == 'test'
